Metadata-Version: 2.1
Name: VisualAssertLibrary
Version: 0.2.8
Summary: Robot Framework Visual Assert Library
Home-page: UNKNOWN
Author: Dmytro Bondarchuk
Author-email: d.bondarchuk.spv@gmail.com
License: UNKNOWN
Platform: UNKNOWN
Classifier: Programming Language :: Python :: 3
Classifier: License :: OSI Approved :: MIT License
